STLtoMask/__init__.py
STLtoMask/color_reader.py
STLtoMask/converter.py
STLtoMask-0.14.dist-info/LICENSE.txt
STLtoMask-0.14.dist-info/METADATA
STLtoMask-0.14.dist-info/WHEEL
STLtoMask-0.14.dist-info/top_level.txt
STLtoMask-0.14.dist-info/RECORD
