Metadata-Version: 2.1
Name: STLtoMask
Version: 0.14
Summary: Convert a STL file into a 3D mask.
Home-page: https://github.com/caleb-oconnor/STLtoMask
Author: Caleb OConnor
Author-email: csoconnor@mdanderson.org
Classifier: Programming Language :: Python :: 3
Classifier: License :: OSI Approved :: GNU Affero General Public License v3
Requires-Python: >=3.7
License-File: LICENSE.txt
